{
  "id": 73301,
  "type": "WQ",
  "series": 73223,
  "titleTextMapHash": 1632930847,
  "descTextMapHash": 1860105990,
  "luaPath": "Actor/Quest/WQ73301",
  "showType": "QUEST_HIDDEN",
  "subQuests": [
    {
      "subId": 7330101,
      "mainId": 73301,
      "order": 1,
      "failParent": 970862500,
      "acceptCondComb": "LOGIC_NONE",
      "finishCondComb": "LOGIC_NONE",
      "acceptCond": [
        {
          "type": "QUEST_COND_UNKNOWN",
          "param": [
            0,
            0
          ]
        }
      ],
      "guide": {},
      "finishCond": [],
      "failCond": [],
      "beginExec": [],
      "finishExec": [],
      "failExec": []
    },
    {
      "subId": 7330102,
      "mainId": 73301,
      "order": 2,
      "failParent": 763774668,
      "acceptCondComb": "LOGIC_NONE",
      "finishCondComb": "LOGIC_NONE",
      "acceptCond": [
        {
          "type": "QUEST_COND_UNKNOWN",
          "param": [
            0,
            0
          ]
        }
      ],
      "guide": {},
      "finishCond": [],
      "failCond": [],
      "beginExec": [],
      "finishExec": [],
      "failExec": []
    }
  ]
}