{
  "id": 73318,
  "type": "WQ",
  "titleTextMapHash": 1982724503,
  "descTextMapHash": 1727026054,
  "luaPath": "Actor/Quest/WQ73318",
  "rewardIdList": [
    173340
  ],
  "chapterId": 10126,
  "subQuests": [
    {
      "mainId": 73318,
      "subId": 7331801,
      "order": 1,
      "showType": "QUEST_HIDDEN",
      "descTextMapHash": 2105589996,
      "acceptCond": [
        {
          "type": "QUEST_COND_UNKNOWN",
          "param": [
            0,
            0
          ]
        }
      ],
      "finishCond": [],
      "failCond": [],
      "guide": {
        "guideLayer": "QUEST_GUIDE_LAYER_UI"
      },
      "finishExec": [],
      "failExec": [],
      "beginExec": []
    },
    {
      "mainId": 73318,
      "subId": 7331802,
      "order": 2,
      "showType": "QUEST_HIDDEN",
      "descTextMapHash": 3946524348,
      "acceptCond": [
        {
          "type": "QUEST_COND_UNKNOWN",
          "param": [
            0,
            0
          ]
        }
      ],
      "finishCond": [],
      "failCond": [],
      "guide": {
        "param": [
          "30"
        ],
        "guideScene": 3,
        "guideLayer": "QUEST_GUIDE_LAYER_UI"
      },
      "finishExec": [],
      "failExec": [],
      "beginExec": []
    },
    {
      "mainId": 73318,
      "subId": 7331803,
      "order": 3,
      "showType": "QUEST_HIDDEN",
      "descTextMapHash": 3639737348,
      "acceptCond": [
        {
          "type": "QUEST_COND_UNKNOWN",
          "param": [
            0,
            0
          ]
        }
      ],
      "finishCond": [],
      "failCond": [],
      "guide": {
        "type": "QUEST_GUIDE_NPC",
        "param": [
          "20987"
        ],
        "guideScene": 3,
        "guideStyle": "QUEST_GUIDE_STYLE_TARGET",
        "guideLayer": "QUEST_GUIDE_LAYER_UI"
      },
      "finishExec": [],
      "failExec": [],
      "beginExec": []
    },
    {
      "mainId": 73318,
      "subId": 7331804,
      "order": 5,
      "descTextMapHash": 417311820,
      "acceptCond": [
        {
          "type": "QUEST_COND_UNKNOWN",
          "param": [
            0,
            0
          ]
        }
      ],
      "finishCond": [],
      "failCond": [],
      "guide": {
        "type": "QUEST_GUIDE_LOCATION",
        "param": [
          "Q7331804_guide",
          "30"
        ],
        "guideScene": 3,
        "guideStyle": "QUEST_GUIDE_STYLE_POINT",
        "guideLayer": "QUEST_GUIDE_LAYER_UI"
      },
      "finishExec": [],
      "failExec": [],
      "beginExec": []
    },
    {
      "mainId": 73318,
      "subId": 7331805,
      "order": 6,
      "descTextMapHash": 1702256956,
      "acceptCond": [
        {
          "type": "QUEST_COND_UNKNOWN",
          "param": [
            0,
            0
          ]
        }
      ],
      "finishCond": [],
      "failCond": [],
      "guide": {
        "type": "QUEST_GUIDE_NPC",
        "param": [
          "20953"
        ],
        "guideScene": 3,
        "guideStyle": "QUEST_GUIDE_STYLE_TARGET",
        "guideLayer": "QUEST_GUIDE_LAYER_UI"
      },
      "finishExec": [],
      "failExec": [],
      "beginExec": []
    },
    {
      "mainId": 73318,
      "subId": 7331806,
      "order": 7,
      "descTextMapHash": 285712356,
      "acceptCond": [
        {
          "type": "QUEST_COND_UNKNOWN",
          "param": [
            0,
            0
          ]
        }
      ],
      "finishCond": [],
      "failCond": [],
      "guide": {
        "type": "QUEST_GUIDE_LOCATION",
        "param": [
          "Q7331804_guide",
          "50"
        ],
        "guideScene": 3,
        "guideStyle": "QUEST_GUIDE_STYLE_POINT",
        "guideLayer": "QUEST_GUIDE_LAYER_UI"
      },
      "finishExec": [],
      "failExec": [],
      "beginExec": []
    },
    {
      "mainId": 73318,
      "subId": 7331807,
      "order": 11,
      "descTextMapHash": 162708772,
      "acceptCond": [
        {
          "type": "QUEST_COND_UNKNOWN",
          "param": [
            0,
            0
          ]
        }
      ],
      "finishCond": [],
      "failCond": [],
      "guide": {
        "type": "QUEST_GUIDE_NPC",
        "param": [
          "20953"
        ],
        "guideScene": 3,
        "guideStyle": "QUEST_GUIDE_STYLE_TARGET",
        "guideLayer": "QUEST_GUIDE_LAYER_UI"
      },
      "finishExec": [],
      "failExec": [],
      "beginExec": []
    },
    {
      "mainId": 73318,
      "subId": 7331808,
      "order": 4,
      "showType": "QUEST_HIDDEN",
      "descTextMapHash": 2069854844,
      "acceptCond": [
        {
          "type": "QUEST_COND_UNKNOWN",
          "param": [
            0,
            0
          ]
        }
      ],
      "finishCond": [],
      "failCond": [],
      "guide": {
        "guideLayer": "QUEST_GUIDE_LAYER_UI"
      },
      "finishExec": [],
      "failExec": [],
      "beginExec": []
    },
    {
      "mainId": 73318,
      "subId": 7331809,
      "order": 12,
      "showType": "QUEST_HIDDEN",
      "descTextMapHash": 1556228564,
      "acceptCond": [
        {
          "type": "QUEST_COND_UNKNOWN",
          "param": [
            0,
            0
          ]
        }
      ],
      "finishCond": [],
      "failCond": [],
      "guide": {},
      "finishExec": [],
      "failExec": [],
      "beginExec": []
    },
    {
      "mainId": 73318,
      "subId": 7331810,
      "order": 8,
      "descTextMapHash": 2967731340,
      "acceptCond": [
        {
          "type": "QUEST_COND_UNKNOWN",
          "param": [
            0,
            0
          ]
        }
      ],
      "finishCond": [],
      "failCond": [],
      "guide": {
        "type": "QUEST_GUIDE_LOCATION",
        "param": [
          "Q7331804_guide",
          "50"
        ],
        "guideScene": 3,
        "guideStyle": "QUEST_GUIDE_STYLE_POINT",
        "guideLayer": "QUEST_GUIDE_LAYER_UI"
      },
      "finishExec": [],
      "failExec": [],
      "beginExec": []
    },
    {
      "mainId": 73318,
      "subId": 7331811,
      "order": 9,
      "descTextMapHash": 1077277972,
      "acceptCond": [
        {
          "type": "QUEST_COND_UNKNOWN",
          "param": [
            0,
            0
          ]
        }
      ],
      "finishCond": [],
      "failCond": [],
      "guide": {
        "type": "QUEST_GUIDE_LOCATION",
        "param": [
          "Q7331804_guide",
          "50"
        ],
        "guideScene": 3,
        "guideStyle": "QUEST_GUIDE_STYLE_POINT",
        "guideLayer": "QUEST_GUIDE_LAYER_UI"
      },
      "finishExec": [],
      "failExec": [],
      "beginExec": []
    },
    {
      "mainId": 73318,
      "subId": 7331813,
      "order": 10,
      "showType": "QUEST_HIDDEN",
      "descTextMapHash": 2941577660,
      "acceptCond": [
        {
          "type": "QUEST_COND_UNKNOWN",
          "param": [
            0,
            0
          ]
        }
      ],
      "finishCond": [],
      "failCond": [],
      "guide": {},
      "finishExec": [],
      "failExec": [],
      "beginExec": []
    }
  ],
  "talks": [
    {
      "id": 7331802,
      "beginWay": "TALK_BEGIN_MANUAL",
      "activeMode": "PLAY_MODE_HOST",
      "beginCondComb": "LOGIC_AND",
      "beginCond": [
        {
          "type": "QUEST_COND_STATE_EQUAL",
          "param": [
            "7331803",
            "2"
          ],
          "param_str": ""
        },
        {
          "type": "QUEST_COND_QUEST_GLOBAL_VAR_EQUAL",
          "param": [
            "7325103",
            "1"
          ],
          "param_str": ""
        }
      ],
      "priority": 5,
      "initDialog": 733180201,
      "npcId": [
        20987
      ],
      "performCfg": "QuestDialogue/WQ/Sumeru_73318/Q7331802",
      "heroTalk": "TALK_HERO_MAIN",
      "questId": 73318,
      "prePerformCfg": ""
    },
    {
      "id": 7331803,
      "beginWay": "TALK_BEGIN_MANUAL",
      "activeMode": "PLAY_MODE_HOST",
      "beginCondComb": "LOGIC_AND",
      "beginCond": [
        {
          "type": "QUEST_COND_STATE_EQUAL",
          "param": [
            "7331803",
            "2"
          ],
          "param_str": ""
        },
        {
          "type": "QUEST_COND_QUEST_GLOBAL_VAR_EQUAL",
          "param": [
            "7325103",
            "0"
          ],
          "param_str": ""
        }
      ],
      "priority": 5,
      "initDialog": 733180301,
      "npcId": [
        20987
      ],
      "performCfg": "QuestDialogue/WQ/Sumeru_73318/Q7331803",
      "heroTalk": "TALK_HERO_MAIN",
      "questId": 73318,
      "prePerformCfg": ""
    },
    {
      "id": 7331805,
      "beginWay": "TALK_BEGIN_MANUAL",
      "activeMode": "PLAY_MODE_HOST",
      "beginCond": [
        {
          "type": "QUEST_COND_STATE_EQUAL",
          "param": [
            "7331805",
            "2"
          ],
          "param_str": ""
        }
      ],
      "priority": 5,
      "initDialog": 733180501,
      "npcId": [
        20953
      ],
      "performCfg": "QuestDialogue/WQ/Sumeru_73318/Q7331805",
      "heroTalk": "TALK_HERO_MAIN",
      "questId": 73318,
      "prePerformCfg": "",
      "talkMarkType": "TALK_MARK_COMMON"
    },
    {
      "id": 7331807,
      "beginWay": "TALK_BEGIN_MANUAL",
      "activeMode": "PLAY_MODE_HOST",
      "beginCond": [
        {
          "type": "QUEST_COND_STATE_EQUAL",
          "param": [
            "7331807",
            "2"
          ],
          "param_str": ""
        }
      ],
      "priority": 5,
      "initDialog": 733180701,
      "npcId": [
        20953
      ],
      "performCfg": "QuestDialogue/WQ/Sumeru_73318/Q7331807",
      "heroTalk": "TALK_HERO_MAIN",
      "questId": 73318,
      "prePerformCfg": ""
    },
    {
      "id": 7331820,
      "beginWay": "TALK_BEGIN_MANUAL",
      "activeMode": "PLAY_MODE_HOST",
      "beginCondComb": "LOGIC_OR",
      "beginCond": [
        {
          "type": "QUEST_COND_STATE_EQUAL",
          "param": [
            "7331807",
            "2"
          ],
          "param_str": ""
        },
        {
          "type": "QUEST_COND_QUEST_NOT_RECEIVE",
          "param": [
            "7331807",
            "1"
          ],
          "param_str": ""
        }
      ],
      "priority": 3,
      "initDialog": 733182001,
      "npcId": [
        20953
      ],
      "performCfg": "",
      "heroTalk": "TALK_HERO_MAIN",
      "questId": 73318,
      "prePerformCfg": "",
      "questIdleTalk": true,
      "lowPriority": true
    }
  ]
}